file_sync_tool/__init__.py
file_sync_tool/__main__.py
file_sync_tool/info.py
file_sync_tool/sync.py
file_sync_tool/transfer/__init__.py
file_sync_tool/transfer/process.py
file_sync_tool/transfer/utility.py
file_sync_tool/utility/__init__.py
file_sync_tool/utility/helper.py
file_sync_tool/utility/info.py
file_sync_tool_kmi-0.4.9.dist-info/licenses/LICENSE
file_sync_tool_kmi-0.4.9.dist-info/METADATA
file_sync_tool_kmi-0.4.9.dist-info/WHEEL
file_sync_tool_kmi-0.4.9.dist-info/entry_points.txt
file_sync_tool_kmi-0.4.9.dist-info/top_level.txt
file_sync_tool_kmi-0.4.9.dist-info/RECORD
